saconvert/__init__.py
saconvert/conversions.py
saconvert-0.1.2.dist-info/METADATA
saconvert-0.1.2.dist-info/WHEEL
saconvert-0.1.2.dist-info/top_level.txt
saconvert-0.1.2.dist-info/RECORD
