Metadata-Version: 2.1
Name: saconvert
Version: 0.1.2
Summary: saconvert is a versatile Python library focused on conversions, providing a seamless interface to effortlessly convert between weight and length units. With a growing list of upcoming conversions, saconvert simplifies complex transformations, making it a must-have tool for developers and engineers working with measurements. Empower your projects with the efficiency and precision of saconvert, and stay tuned for new exciting conversion features to be added soon!
Home-page: https://github.com/yourusername/conversions
Author: Skanda Acharya
Author-email: skanda.acharya@yahoo.com
